geoiter/__init__.py
geoiter/geoiter.py
geoiter/util/gpx.py
geoiter/util/plot.py
geoiter/util/ressource_example.py
geoiter-0.1.1.dist-info/LICENSE.md
geoiter-0.1.1.dist-info/METADATA
geoiter-0.1.1.dist-info/WHEEL
geoiter-0.1.1.dist-info/top_level.txt
geoiter-0.1.1.dist-info/RECORD
