Metadata-Version: 2.1
Name: geoiter
Version: 0.1.1
Summary: A simple tool to iterate circles within given boundaries:
Home-page: https://github.com/cloasdata/geoiter
Author: Simon Bauer
Author-email: code@seimenadventure.de
License: MIT
Keywords: iter,geo,scraping,data
Platform: UNKNOWN
Classifier: Programming Language :: Python :: 3
Classifier: License :: OSI Approved :: MIT License
Classifier: Operating System :: OS Independent
License-File: LICENSE.md
Requires-Dist: haversine (>=2.5.1)
Requires-Dist: importlib ; python_version >= "3.10"
Provides-Extra: gpx
Requires-Dist: lxml (>=4.8.0) ; extra == 'gpx'
Provides-Extra: overpass
Requires-Dist: httpx (>=0.22.0) ; extra == 'overpass'
Provides-Extra: plot
Requires-Dist: cartopy (>=0.20.2) ; extra == 'plot'
Requires-Dist: descartes (>=1.1.0) ; extra == 'plot'
Provides-Extra: test
Requires-Dist: pytest (>=7.0.0) ; extra == 'test'
Requires-Dist: pytest-benchmark (>=3.4.1) ; extra == 'test'
